{
	"input":[
	{
		"dbcolumn": "G_ALAM_", 
		"datatype": "discrete"
	},
	{
		"dbcolumn": "G_PRGM_", 
		"datatype": "text"
	},
	{
		"dbcolumn": "G_CONS_", 
		"datatype": "discrete"
	},
	{
		"dbcolumn": "G_AUMO_", 
		"datatype": "discrete"
	},
	{
		"dbcolumn": "G_PARA_6750_6750_N", 
		"datatype": "continuous"
	},
	{
		"dbcolumn": "G_PARA_6751_6751_N", 
		"datatype": "continuous"
	},
	{
		"dbcolumn": "G_MODA_", 
		"datatype": "text"
	},
	{
		"dbcolumn": "G_POSM_T", 
		"datatype": "text"
	},
	{
		"dbcolumn": "G_POSR_T", 
		"datatype": "text"
	},
	{
		"dbcolumn": "G_POSA_T", 
		"datatype": "text"
	},
	{
		"dbcolumn": "G_POSD_T", 
		"datatype": "text"
	},
	{
		"dbcolumn": "G_ACTF_", 
		"datatype": "continuous"
	},
	{
		"dbcolumn": "G_FERP_", 
		"datatype": "continuous"
	},
	{
		"dbcolumn": "G_EXEP_", 
		"datatype": "discrete"
	},
	{
		"dbcolumn": "G_TOFS_1_32", 
		"datatype": "text"
	},
	{
		"dbcolumn": "G_PICH_0_1023", 
		"datatype": "text"
	},
	{
		"dbcolumn": "G_ZOFS_0_6", 
		"datatype": "text"
	},
	{
		"dbcolumn": "G_ACTS_", 
		"datatype": "continuous"
	},
	{
		"dbcolumn": "G_SPMS_", 
		"datatype": "continuous"
	},
	{
		"dbcolumn": "G_SPSD_", 
		"datatype": "continuous"
	},
	{
		"dbcolumn": "G_SPMC_", 
		"datatype": "continuous"
	},
	{
		"dbcolumn": "G_SRAC_", 
		"datatype": "text"
	}
	],
	"action":{
		"type" : "association",
		"kernel_type" : "MEM",
    	"parameter":{
        	"Support_threshold" : 0.1,
        	"Confidence_threshold" : 0.9
      	}
	
}